[
  {
    "color": 79,
    "js": " lastfill = c.fillStyle;\n c.fillStyle = '#4F4F4F';\n c.fillRect(0,0,cw.width, cw.height);\n c.fillStyle = lastfill;",
    "id": 98,
    "instruccion": "fondo"
  },
  {
    "js": "c.fillStyle = \"#F0CB38\";",
    "id": 102,
    "colorh": "FFF0CB38",
    "instruccion": "relleno"
  },
  {
    "tx": 50,
    "ty": 50,
    "js": " c.fillRect(ratonX, ratonY, 50, 50);\n c.strokeRect(ratonX, ratonY, 50, 50);\n",
    "id": 114,
    "pyv": "ratonY",
    "instruccion": "rectangulo",
    "pxv": "ratonX"
  },
  {
    "js": "c.fillStyle = \"#47D938\";",
    "id": 102,
    "colorh": "FF47D938",
    "instruccion": "relleno"
  },
  {
    "tx": 300,
    "ty": 300,
    "px": 100,
    "py": 100,
    "js": " c.fillRect(100, 100, 300, 300);\n c.strokeRect(100, 100, 300, 300);\n",
    "id": 114,
    "instruccion": "rectangulo"
  },
  {
    "js": "c.fillStyle = \"#DECF38\";",
    "id": 102,
    "colorh": "FFDECF38",
    "instruccion": "relleno"
  },
  {
    "tx": 40,
    "ty": 40,
    "js": " c.beginPath();\n c.ellipse(ratonX, ratonY, 40, 40, 0, 0, Math.PI*2);\n c.fill();\n c.stroke();\n c.closePath();\n",
    "id": 101,
    "pyv": "ratonY",
    "instruccion": "elipse",
    "pxv": "ratonX"
  },
  {
    "js": "c.fillStyle = \"#FFC138\";",
    "id": 102,
    "colorh": "FFFFC138",
    "instruccion": "relleno"
  },
  {
    "pxt1": 10,
    "pyt1": 10,
    "pxt2": 500,
    "pyt2": 500,
    "pxt3": 0,
    "js": "c.beginPath();\n c.moveTo(10,10);\n c.lineTo(500,500);\n c.lineTo(0,700);\n c.fill();\n c.moveTo(10,10);\n c.lineTo(500,500);\n c.lineTo(0,700);\n c.closePath();\n c.stroke();\n",
    "id": 51,
    "pyt3": 700,
    "instruccion": "triangulo"
  },
  {
    "color": 254,
    "js": "c.strokeStyle = \"#FEFEFE\";",
    "id": 115,
    "instruccion": "colorlinea"
  },
  {
    "pxt2v": "ratonX",
    "pxt1v": "ancho",
    "pyt1v": "alto",
    "js": "c.beginPath();\n c.moveTo(ancho, alto);\n c.lineTo(ratonX, ratonY);\n c.stroke();",
    "id": 108,
    "pyt2v": "ratonY",
    "instruccion": "linea"
  },
  {
    "px": 50,
    "py": 200,
    "js": "var image = new Image();\n   image.src = 'data/logolab.png';\n   c.drawImage(image, 50, 200);\n",
    "id": 109,
    "nombre": "logolab.png",
    "instruccion": "imagen"
  },
  {
    "color": 254,
    "js": "c.fillStyle = \"#FEFEFE\";",
    "id": 102,
    "instruccion": "relleno"
  },
  {
    "tamtexto": "66",
    "js": "c.font = '66px sans-serif';",
    "id": 117,
    "instruccion": "tamtexto"
  },
  {
    "texto": "Meta_Javascript",
    "px": 60,
    "py": 60,
    "js": "c.fillText(\"Meta_Javascript\",60, 60);",
    "id": 116,
    "instruccion": "texto"
  }
]